confluentfucci/__init__.py
confluentfucci/data.py
confluentfucci/gui.py
confluentfucci/math.py
confluentfucci/utils.py
confluentfucci-1.1.1.dist-info/LICENSE.txt
confluentfucci-1.1.1.dist-info/METADATA
confluentfucci-1.1.1.dist-info/WHEEL
confluentfucci-1.1.1.dist-info/RECORD
