Metadata-Version: 2.1
Name: confluentfucci
Version: 1.1.1
Summary: 
Author: Leo Goldstien
Author-email: leogoldstien@gmail.com
Requires-Python: >=3.10,<4.0
Classifier: Programming Language :: Python :: 3
Classifier: Programming Language :: Python :: 3.10
Classifier: Programming Language :: Python :: 3.11
Requires-Dist: aicsimageio (>=4.11.0,<5.0.0)
Requires-Dist: botocore (==1.27.26)
Requires-Dist: cellpose (==2.1.0)
Requires-Dist: dask-image (>=2023.3.0,<2024.0.0)
Requires-Dist: docker (>=6.1.3,<7.0.0)
Requires-Dist: h5py (>=3.9.0,<4.0.0)
Requires-Dist: holoviews (>=1.16.2,<2.0.0)
Requires-Dist: hvplot (>=0.8.4,<0.9.0)
Requires-Dist: imagecodecs (==2023.9.18)
Requires-Dist: loguru (>=0.7.0,<0.8.0)
Requires-Dist: napari[all] (>=0.4.18,<0.5.0)
Requires-Dist: pandas (==1.4.3)
Requires-Dist: panel (==0.13.1)
Requires-Dist: shapely (>=2.0.1,<3.0.0)
Requires-Dist: tables (>=3.8.0,<4.0.0)
Requires-Dist: tifffile (==2022.5.4)
Requires-Dist: torch (==1.13.1) ; sys_platform == "darwin"
Requires-Dist: torch (==1.13.1) ; sys_platform == "linux"
Requires-Dist: torch (==1.13.1) ; sys_platform == "win32"
